beyondmail/__init__.py
beyondmail/host.py
beyondmail/mail.py
beyondmail-0.1.4.dist-info/METADATA
beyondmail-0.1.4.dist-info/WHEEL
beyondmail-0.1.4.dist-info/RECORD
