Metadata-Version: 2.1
Name: beyondmail
Version: 0.1.4
Summary: Beyond Mail its an open source project made for sending emails easily with python.
Author: Davi Lucciola
Author-email: davilucciola14@gmail.com
Requires-Python: >=3.10,<4.0
Classifier: Programming Language :: Python :: 3
Classifier: Programming Language :: Python :: 3.10
Classifier: Programming Language :: Python :: 3.11
